[
  {
    "filename": "case_490.json",
    "cu": {
      "modified_key": "security.ciphering_algorithms[0]",
      "original_value": "nea3",
      "error_value": "nea5",
      "error_type": "invalid_enum",
      "explanation_en": "Setting the ciphering algorithm to 'nea5' which is not a supported enum value will cause security negotiation failures and prevent UE attachment."
    },
    "du": {
      "modified_key": "fhi_72.fh_config[0].T1a_cp_dl[0]",
      "original_value": 285,
      "error_value": 1000,
      "error_type": "out_of_range",
      "explanation_en": "Setting the T1a_cp_dl timing parameter to 1000 exceeds the valid range, causing timing misalignment and front-haul synchronization issues."
    }
  }
]
