[
  {
    "filename": "case_080.json",
    "cu": {
      "modified_key": "Num_Threads_PUSCH",
      "original_value": 8,
      "error_value": 0,
      "error_type": "zero_value",
      "explanation": "Setting Zero value where positive required for Num_Threads_PUSCH causes runtime failure in CU module"
    },
    "du": {
      "modified_key": "RUs[0].nb_tx",
      "original_value": 4,
      "error_value": 0,
      "error_type": "zero_value",
      "explanation": "Setting Zero value where positive required for RUs[0].nb_tx causes runtime failure in DU module"
    }
  }
]